Dummy
ROOT
cppyy
