Metadata-Version: 2.1
Name: ROOT
Version: 0.1a8
Summary: An open-source data analysis framework used by high energy physics and others.
Maintainer-email: Vincenzo Eduardo Padulano <vincenzo.eduardo.padulano@cern.ch>
License: This library is free software; you can redistribute it and/or
Requires-Python: >=3.8
License-File: LICENSE
Requires-Dist: numpy
